airflow_docker/__init__.py
airflow_docker/conf.py
airflow_docker/operator.py
airflow_docker/plugin.py
airflow_docker/utils.py
airflow_docker/ext/__init__.py
airflow_docker/ext/environment_preset.py
airflow_docker/ext/aws/__init__.py
airflow_docker/ext/aws/role_assumption.py
airflow_docker/views/__init__.py
airflow_docker/views/config.py
airflow_docker/views/extensions.py
airflow_docker/views/templates/__init__.py
airflow_docker/views/templates/config.html
airflow_docker/views/templates/extensions.html
airflow_docker-2.1.1.dist-info/LICENSE
airflow_docker-2.1.1.dist-info/METADATA
airflow_docker-2.1.1.dist-info/WHEEL
airflow_docker-2.1.1.dist-info/entry_points.txt
airflow_docker-2.1.1.dist-info/top_level.txt
airflow_docker-2.1.1.dist-info/RECORD
