Metadata-Version: 2.1
Name: airflow-docker
Version: 2.1.1
Summary: An opinionated implementation of exclusively using airflow DockerOperators for all Operators
Home-page: https://github.com/huntcsg/airflow-docker
Author: Hunter Senft-Grupp
Author-email: huntcsg@gmail.com
License: Apache License 2.0
Keywords: airflow docker
Platform: UNKNOWN
Classifier: Development Status :: 3 - Alpha
Classifier: Environment :: Console
Classifier: Environment :: Web Environment
Classifier: Intended Audience :: Developers
Classifier: Intended Audience :: System Administrators
Classifier: License :: OSI Approved :: Apache Software License
Classifier: Programming Language :: Python :: 3.6
Classifier: Programming Language :: Python :: 3.7
Classifier: Topic :: System :: Monitoring
Requires-Python: >=3,!=3.0.*,!=3.1.*,!=3.2.*,!=3.3.*,!=3.4.*,!=3.5.*
Requires-Dist: apache-airflow[celery,docker] (==1.10.9)
Requires-Dist: airflow-docker-helper (>=0.2.0)
Requires-Dist: airflow-queue-stats (==0.1.4)
Requires-Dist: boto3
Provides-Extra: dev
Requires-Dist: releasely (>=1.1) ; extra == 'dev'
Provides-Extra: docs
Requires-Dist: sphinx ; extra == 'docs'
Requires-Dist: sphinx-rtd-theme ; extra == 'docs'
Provides-Extra: linting
Requires-Dist: isort ; extra == 'linting'
Requires-Dist: black ; extra == 'linting'
Requires-Dist: flake8 ; extra == 'linting'
Provides-Extra: testing
Requires-Dist: pytest ; extra == 'testing'
Requires-Dist: pytest-cov ; extra == 'testing'
Requires-Dist: mock ; (python_version < "3") and extra == 'testing'
